{
  "provider": {
    "id": "royal-caribbean",
    "name": "Royal Caribbean"
  },
  "count": 2,
  "cruises": [
    {
      "provider": "Royal Caribbean",
      "id": "rc_VI10BWI-257737393",
      "shipName": "Vision of the Seas",
      "shipClass": "Vision",
      "shipLaunchYear": 1998,
      "itinerary": "Baltimore To San Juan Cruise: Baltimore, Maryland, Grand Turk, Turks & Caicos, Philipsburg, St. Maarten, Roseau, Dominica, Fort de France, Martinique, St. John's, Antigua, Tortola, British Virgin Islands, San Juan, Puerto Rico",
      "departureDate": "2026-10-22",
      "duration": "10 Nights",
      "departurePort": "Baltimore",
      "departureRegion": "Americas",
      "destination": "Repositioning",
      "priceFrom": "2309",
      "currency": "GBP",
      "bookingUrl": "https://www.royalcaribbean.com/booking/landing?groupId=VI10BWI-257737393&sailDate=2026-10-22&shipCode=VI&packageCode=VI10R040&destinationCode=ISLAN&selectedCurrencyCode=GBP&country=GBR",
      "prices": {
        "inside": null,
        "oceanView": null,
        "balcony": null,
        "suite": "2309"
      },
      "destinationPort": "San Juan",
      "seaDays": 2,
      "enrichedAt": "2026-07-15T18:27:10.759Z",
      "firstSeenAt": "2026-05-29T09:33:04.484Z",
      "lastSeenAt": "2026-07-18T20:16:51.360Z",
      "priceHistory": [
        {
          "at": "2026-05-29T18:29:37.417Z",
          "prices": {
            "inside": 1148.9
          }
        },
        {
          "at": "2026-05-30T19:06:05.550Z",
          "prices": {
            "inside": 1197.9
          }
        },
        {
          "at": "2026-05-31T12:12:25.302Z",
          "prices": {
            "inside": 901.5
          }
        },
        {
          "at": "2026-05-31T13:26:40.132Z",
          "prices": {
            "inside": 903.5
          }
        },
        {
          "at": "2026-06-01T03:33:08.553Z",
          "prices": {
            "inside": 864.5
          }
        },
        {
          "at": "2026-06-01T20:13:35.019Z",
          "prices": {
            "inside": 881.5
          }
        },
        {
          "at": "2026-06-02T18:05:24.346Z",
          "prices": {
            "inside": 881.5,
            "suite": 2326.5
          }
        },
        {
          "at": "2026-06-03T19:45:18.339Z",
          "prices": {
            "inside": 896.5,
            "suite": 2324.5
          }
        },
        {
          "at": "2026-06-04T03:32:48.128Z",
          "prices": {
            "inside": 941.5,
            "suite": 2324.5
          }
        },
        {
          "at": "2026-06-04T16:51:20.118Z",
          "prices": {
            "inside": 941.5
          }
        },
        {
          "at": "2026-06-04T19:59:26.626Z",
          "prices": {
            "inside": 896.5,
            "oceanView": 1130.5,
            "balcony": 2307.5,
            "suite": 4148.5
          }
        },
        {
          "at": "2026-06-04T21:46:19.713Z",
          "prices": {
            "inside": 896.5,
            "oceanView": 1130.5,
            "balcony": 2307.5,
            "suite": 4166
          }
        },
        {
          "at": "2026-06-06T15:10:22.563Z",
          "prices": {
            "inside": 941.5,
            "oceanView": 1130.5,
            "balcony": 2307.5,
            "suite": 4166
          }
        },
        {
          "at": "2026-06-06T19:14:21.054Z",
          "prices": {
            "inside": 941.5,
            "oceanView": 1130.5,
            "balcony": 2293.5,
            "suite": 4166
          }
        },
        {
          "at": "2026-06-07T19:14:50.671Z",
          "prices": {
            "inside": 948.5,
            "oceanView": 1130.5,
            "balcony": 2293.5,
            "suite": 4166
          }
        },
        {
          "at": "2026-06-07T21:06:57.036Z",
          "prices": {
            "inside": 948.5,
            "oceanView": 1130.5,
            "suite": 4166
          }
        },
        {
          "at": "2026-06-08T14:03:15.130Z",
          "prices": {
            "inside": 948.5,
            "suite": 4166
          }
        },
        {
          "at": "2026-06-08T18:22:55.802Z",
          "prices": {
            "inside": 916.5,
            "suite": 4153
          }
        },
        {
          "at": "2026-06-08T21:48:00.276Z",
          "prices": {
            "inside": 916.5,
            "suite": 4075.5
          }
        },
        {
          "at": "2026-06-09T18:52:55.794Z",
          "prices": {
            "inside": 946.5,
            "suite": 4075.5
          }
        },
        {
          "at": "2026-06-10T05:32:54.965Z",
          "prices": {
            "suite": 4075.5
          }
        },
        {
          "at": "2026-06-11T17:15:28.137Z",
          "prices": {
            "inside": 946.5,
            "suite": 4075.5
          }
        },
        {
          "at": "2026-06-11T22:36:23.717Z",
          "prices": {
            "inside": 946.5,
            "suite": 4115.5
          }
        },
        {
          "at": "2026-06-13T20:29:37.518Z",
          "prices": {
            "inside": 984.5,
            "suite": 4115.5
          }
        },
        {
          "at": "2026-06-14T14:47:05.414Z",
          "prices": {
            "inside": 984.5
          }
        },
        {
          "at": "2026-06-15T00:47:54.065Z",
          "prices": {
            "inside": 984.5,
            "suite": 2271.5
          }
        },
        {
          "at": "2026-06-15T14:07:34.201Z",
          "prices": {
            "inside": 984.5
          }
        },
        {
          "at": "2026-06-15T17:40:31.110Z",
          "prices": {
            "inside": 990.5,
            "suite": 4143.5
          }
        },
        {
          "at": "2026-06-15T22:41:56.222Z",
          "prices": {
            "suite": 4161
          }
        },
        {
          "at": "2026-06-16T00:52:58.946Z",
          "prices": {
            "inside": 990.5
          }
        },
        {
          "at": "2026-06-18T07:41:29.008Z",
          "prices": {
            "inside": 997.5
          }
        },
        {
          "at": "2026-06-21T07:38:44.706Z",
          "prices": {
            "inside": 1022.5
          }
        },
        {
          "at": "2026-06-23T05:22:02.135Z",
          "prices": {
            "inside": 1013.5
          }
        },
        {
          "at": "2026-07-01T18:40:09.630Z",
          "prices": {
            "oceanView": 1437.5
          }
        },
        {
          "at": "2026-07-04T05:16:50.049Z",
          "prices": {
            "suite": 2426.5
          }
        },
        {
          "at": "2026-07-07T05:20:16.655Z",
          "prices": {
            "oceanView": 1442.5
          }
        },
        {
          "at": "2026-07-10T06:40:41.897Z",
          "prices": {
            "suite": 2261
          }
        },
        {
          "at": "2026-07-12T05:04:49.289Z",
          "prices": {
            "suite": 3202
          }
        },
        {
          "at": "2026-07-12T14:30:43.836Z",
          "prices": {
            "suite": 2310
          }
        },
        {
          "at": "2026-07-13T05:10:33.508Z",
          "prices": {
            "oceanView": 1425
          }
        },
        {
          "at": "2026-07-14T06:45:02.062Z",
          "prices": {
            "suite": 2296.5
          }
        },
        {
          "at": "2026-07-15T18:25:02.237Z",
          "prices": {
            "suite": 3976.5
          }
        },
        {
          "at": "2026-07-15T22:21:07.087Z",
          "prices": {
            "suite": 2326.5
          }
        },
        {
          "at": "2026-07-16T14:40:38.141Z",
          "prices": {
            "suite": 2422.5
          }
        },
        {
          "at": "2026-07-16T18:25:17.642Z",
          "prices": {
            "suite": 2326.5
          }
        },
        {
          "at": "2026-07-16T22:21:11.294Z",
          "prices": {
            "suite": 2309
          }
        }
      ]
    },
    {
      "provider": "Royal Caribbean",
      "id": "rc_SR07YVR-3380411548",
      "shipName": "Serenade of the Seas",
      "shipClass": "Radiance",
      "shipLaunchYear": 2003,
      "itinerary": "Alaska Inside Passage Cruise: Vancouver, British Columbia, Inside Passage (Cruising), Canada, Sitka, Alaska, Endicott Arm & Dawes Glacier (Cruising), Alaska, Juneau, Alaska, Ketchikan, Alaska, Prince Rupert, British Columbia, Vancouver, British Columbia",
      "departureDate": "2026-08-30",
      "duration": "7 Nights",
      "departurePort": "Vancouver",
      "departureRegion": "Americas",
      "destination": "Alaska",
      "priceFrom": "1905",
      "currency": "GBP",
      "bookingUrl": "https://www.royalcaribbean.com/booking/landing?groupId=SR07YVR-3380411548&sailDate=2026-08-30&shipCode=SR&packageCode=SR07A424&destinationCode=ALCAN&selectedCurrencyCode=GBP&country=GBR",
      "prices": {
        "inside": null,
        "oceanView": null,
        "balcony": "1905",
        "suite": null
      },
      "destinationPort": "Vancouver",
      "seaDays": 0,
      "enrichedAt": "2026-07-19T05:05:42.123Z",
      "firstSeenAt": "2026-07-19T05:04:09.574Z",
      "lastSeenAt": "2026-07-19T12:18:43.072Z",
      "priceHistory": [
        {
          "at": "2026-07-19T05:04:09.574Z",
          "prices": {
            "balcony": 1905
          }
        }
      ]
    }
  ]
}
